{
  "code": "200",
  "message": "成功",
  "data": {
    "sameArray": [
      3,
      2,
      2,
      2
    ],
    "pageFinder": {
      "pageSize": 10,
      "rows": [
        {
          "cellStyleMap": {},
          "key": "20000031162900009033220::06",
          "acctId": "2000000001",
          "custId": "c2000000001",
          "custName": "c2000000001",
          "orgId": "BR_0001",
          "orgNum": 110001,
          "orgName": "测试机构_BR_0001",
          "relaStatus": "06",
          "relaStatusDesc": "修改审批中",
          "validFlg": "1",
          "opeTm": 1585984994000,
          "oprEmpId": "110001",
          "oprEmpName": "测试用户_110001",
          "oprType": "2",
          "bizTypeCd": "06",
          "taskNum": "1000001782",
          "cerNum": "c2000000001",
          "empId": "110001",
          "empName": "测试用户_g001",
          "belongOrgId": "g001",
          "belongOrgNum": "g001",
          "belongOrgName": "测试机构_g001",
          "belongDept": "05",
          "relaRoleId": "001",
          "relaRoleDesc": "营销人",
          "relaRatio": 0.2,
          "effDt": 1585929600000,
          "invalidDt": 32503564800000,
          "relaRatioDesc": "  20",
          "bizType": "公司存款",
          "cerTypeCd": "10",
          "cerTypeDesc": "组织机构代码证",
          "mdfrId": "测试用户_110001",
          "number": "1",
          "modifEffDtFlg": "0"
        },
        {
          "cellStyleMap": {},
          "key": "20000031162900009033220::06",
          "acctId": "2000000002",
          "custId": "c2000000002",
          "custName": "c2000000002",
          "orgId": "BR_0002",
          "orgNum": 110002,
          "orgName": "测试机构_BR_0002",
          "relaStatus": "06",
          "relaStatusDesc": "修改审批中",
          "validFlg": "1",
          "opeTm": 1585984994000,
          "oprEmpId": "110002",
          "oprEmpName": "测试用户_110002",
          "oprType": "2",
          "bizTypeCd": "06",
          "taskNum": "1000001782",
          "cerNum": "c2000000002",
          "empId": "110002",
          "empName": "测试用户_g002",
          "belongOrgId": "g002",
          "belongOrgNum": "g002",
          "belongOrgName": "测试机构_g002",
          "belongDept": "01",
          "relaRoleId": "001",
          "relaRoleDesc": "营销人",
          "relaRatio": 0.1,
          "effDt": 1585929600000,
          "invalidDt": 32503564800000,
          "relaRatioDesc": "  10",
          "bizType": "公司存款",
          "cerTypeCd": "10",
          "cerTypeDesc": "组织机构代码证",
          "mdfrId": "测试用户_110002",
          "number": "1",
          "modifEffDtFlg": "0"
        },
        {
          "cellStyleMap": {},
          "key": "20000031162900009033220::06",
          "acctId": "2000000003",
          "custId": "c2000000003",
          "custName": "c2000000003",
          "orgId": "BR_0003",
          "orgNum": 110003,
          "orgName": "测试机构_BR_0003",
          "relaStatus": "06",
          "relaStatusDesc": "修改审批中",
          "validFlg": "1",
          "opeTm": 1585984994000,
          "oprEmpId": "110003",
          "oprEmpName": "测试用户_110003",
          "oprType": "2",
          "bizTypeCd": "06",
          "taskNum": "1000001782",
          "cerNum": "c2000000003",
          "empId": "110003",
          "empName": "测试用户_g003",
          "belongOrgId": "g003",
          "belongOrgNum": "g003",
          "belongOrgName": "测试机构_g003",
          "belongDept": "04",
          "relaRoleId": "001",
          "relaRoleDesc": "营销人",
          "relaRatio": 0.2,
          "effDt": 1585929600000,
          "invalidDt": 32503564800000,
          "relaRatioDesc": "  20",
          "bizType": "公司存款",
          "cerTypeCd": "10",
          "cerTypeDesc": "组织机构代码证",
          "mdfrId": "测试用户_110003",
          "number": "1",
          "modifEffDtFlg": "0"
        },
        {
          "cellStyleMap": {},
          "key": "01090321000125103001820::06",
          "acctId": "2000000004",
          "custId": "c2000000004",
          "custName": "c2000000004",
          "orgId": "BR_0004",
          "orgNum": 110004,
          "orgName": "测试机构_BR_0004",
          "relaStatus": "03",
          "relaStatusDesc": "关联审批中",
          "validFlg": "1",
          "opeTm": 1577264077000,
          "oprEmpId": "110004",
          "oprEmpName": "测试用户_110004",
          "oprType": "1",
          "bizTypeCd": "06",
          "taskNum": "1000002115",
          "cerNum": "c2000000004",
          "empId": "110004",
          "empName": "测试用户_g004",
          "belongOrgId": "g004",
          "belongOrgNum": "g004",
          "belongOrgName": "测试机构_g004",
          "belongDept": "05",
          "relaRoleId": "002",
          "relaRoleDesc": "维护人",
          "relaRatio": 0.33,
          "effDt": 1577203200000,
          "invalidDt": 32503564800000,
          "relaRatioDesc": "  33",
          "bizType": "公司存款",
          "cerTypeCd": "10",
          "cerTypeDesc": "组织机构代码证",
          "mdfrId": "测试用户_110004",
          "number": "2",
          "modifEffDtFlg": "0"
        },
        {
          "cellStyleMap": {},
          "key": "01090321000125103001820::06",
          "acctId": "2000000005",
          "custId": "c2000000005",
          "custName": "c2000000005",
          "orgId": "BR_0005",
          "orgNum": 110005,
          "orgName": "测试机构_BR_0005",
          "relaStatus": "03",
          "relaStatusDesc": "关联审批中",
          "validFlg": "1",
          "opeTm": 1577264077000,
          "oprEmpId": "110005",
          "oprEmpName": "测试用户_110005",
          "oprType": "1",
          "bizTypeCd": "06",
          "taskNum": "1000002115",
          "cerNum": "c2000000005",
          "empId": "110005",
          "empName": "测试用户_g005",
          "belongOrgId": "g005",
          "belongOrgNum": "g005",
          "belongOrgName": "测试机构_g005",
          "belongDept": "05",
          "relaRoleId": "001",
          "relaRoleDesc": "营销人",
          "relaRatio": 0.2,
          "effDt": 1577203200000,
          "invalidDt": 32503564800000,
          "relaRatioDesc": "  20",
          "bizType": "公司存款",
          "cerTypeCd": "10",
          "cerTypeDesc": "组织机构代码证",
          "mdfrId": "测试用户_110005",
          "number": "2",
          "modifEffDtFlg": "0"
        },
        {
          "cellStyleMap": {},
          "key": "01090343000120109107423_test_10172::06",
          "acctId": "2000000006",
          "custId": "c2000000006",
          "custName": "c2000000006",
          "orgId": "BR_0006",
          "orgNum": 110006,
          "orgName": "测试机构_BR_0006",
          "relaStatus": "03",
          "relaStatusDesc": "关联审批中",
          "validFlg": "1",
          "opeTm": 1577240566000,
          "oprEmpId": "110006",
          "oprEmpName": "测试用户_110006",
          "oprType": "1",
          "bizTypeCd": "06",
          "taskNum": "1000002113",
          "cerNum": "c2000000006",
          "empId": "110006",
          "empName": "测试用户_g006",
          "belongOrgId": "g006",
          "belongOrgNum": "g006",
          "belongOrgName": "测试机构_g006",
          "belongDept": "05",
          "relaRoleId": "001",
          "relaRoleDesc": "营销人",
          "relaRatio": 0.23,
          "effDt": 1577203200000,
          "invalidDt": 32503564800000,
          "relaRatioDesc": "  23",
          "bizType": "公司存款",
          "cerTypeCd": "10",
          "cerTypeDesc": "组织机构代码证",
          "mdfrId": "测试用户_110006",
          "number": "3",
          "modifEffDtFlg": "0"
        },
        {
          "cellStyleMap": {},
          "key": "01090343000120109107423_test_10172::06",
          "acctId": "2000000007",
          "custId": "c2000000007",
          "custName": "c2000000007",
          "orgId": "BR_0007",
          "orgNum": 110007,
          "orgName": "测试机构_BR_0007",
          "relaStatus": "03",
          "relaStatusDesc": "关联审批中",
          "validFlg": "1",
          "opeTm": 1577240566000,
          "oprEmpId": "110007",
          "oprEmpName": "测试用户_110007",
          "oprType": "1",
          "bizTypeCd": "06",
          "taskNum": "1000002113",
          "cerNum": "c2000000007",
          "empId": "110007",
          "empName": "测试用户_g007",
          "belongOrgId": "g007",
          "belongOrgNum": "g007",
          "belongOrgName": "测试机构_g007",
          "belongDept": "04",
          "relaRoleId": "002",
          "relaRoleDesc": "维护人",
          "relaRatio": 0.13,
          "effDt": 1577203200000,
          "invalidDt": 32503564800000,
          "relaRatioDesc": "  13",
          "bizType": "公司存款",
          "cerTypeCd": "10",
          "cerTypeDesc": "组织机构代码证",
          "mdfrId": "测试用户_110007",
          "number": "3",
          "modifEffDtFlg": "0"
        },
        {
          "cellStyleMap": {},
          "key": "01090321000120102096005::06",
          "acctId": "2000000008",
          "custId": "c2000000008",
          "custName": "c2000000008",
          "orgId": "BR_0008",
          "orgNum": 110008,
          "orgName": "测试机构_BR_0008",
          "relaStatus": "06",
          "relaStatusDesc": "修改审批中",
          "validFlg": "1",
          "opeTm": 1573457161000,
          "oprEmpId": "110008",
          "oprEmpName": "测试用户_110008",
          "oprType": "2",
          "bizTypeCd": "06",
          "taskNum": "1000002032",
          "cerNum": "c2000000008",
          "empId": "110008",
          "empName": "测试用户_g008",
          "belongOrgId": "g008",
          "belongOrgNum": "g008",
          "belongOrgName": "测试机构_g008",
          "belongDept": "05",
          "relaRoleId": "002",
          "relaRoleDesc": "维护人",
          "relaRatio": 0.13,
          "effDt": 1573401600000,
          "invalidDt": 32503564800000,
          "relaRatioDesc": "  13",
          "bizType": "公司存款",
          "cerTypeCd": "10",
          "cerTypeDesc": "组织机构代码证",
          "mdfrId": "测试用户_110008",
          "number": "4",
          "modifEffDtFlg": "0"
        },
        {
          "cellStyleMap": {},
          "key": "01090321000120102096005::06",
          "acctId": "2000000009",
          "custId": "c2000000009",
          "custName": "c2000000009",
          "orgId": "BR_0009",
          "orgNum": 110009,
          "orgName": "测试机构_BR_0009",
          "relaStatus": "06",
          "relaStatusDesc": "修改审批中",
          "validFlg": "1",
          "opeTm": 1573457161000,
          "oprEmpId": "110009",
          "oprEmpName": "测试用户_110009",
          "oprType": "2",
          "bizTypeCd": "06",
          "taskNum": "1000002032",
          "cerNum": "c2000000009",
          "empId": "110009",
          "empName": "测试用户_g009",
          "belongOrgId": "g009",
          "belongOrgNum": "g009",
          "belongOrgName": "测试机构_g009",
          "belongDept": "05",
          "relaRoleId": "001",
          "relaRoleDesc": "营销人",
          "relaRatio": 0.33,
          "effDt": 1573401600000,
          "invalidDt": 32503564800000,
          "relaRatioDesc": "  33",
          "bizType": "公司存款",
          "cerTypeCd": "10",
          "cerTypeDesc": "组织机构代码证",
          "mdfrId": "测试用户_110009",
          "number": "4",
          "modifEffDtFlg": "0"
        },
        {
          "cellStyleMap": {},
          "key": "01090321000120102108561::06",
          "acctId": "2000000010",
          "custId": "c2000000010",
          "custName": "c2000000010",
          "orgId": "BR_0010",
          "orgNum": 110010,
          "orgName": "测试机构_BR_0010",
          "relaStatus": "03",
          "relaStatusDesc": "关联审批中",
          "validFlg": "1",
          "opeTm": 1573454242000,
          "oprEmpId": "110010",
          "oprEmpName": "测试用户_110010",
          "oprType": "1",
          "bizTypeCd": "06",
          "taskNum": "1000002022",
          "cerNum": "c2000000010",
          "empId": "110010",
          "empName": "测试用户_g010",
          "belongOrgId": "g010",
          "belongOrgNum": "g010",
          "belongOrgName": "测试机构_g010",
          "belongDept": "05",
          "relaRoleId": "001",
          "relaRoleDesc": "营销人",
          "relaRatio": 0.1,
          "effDt": 1572883200000,
          "invalidDt": 32503564800000,
          "relaRatioDesc": "  10",
          "bizType": "公司存款",
          "cerTypeCd": "10",
          "cerTypeDesc": "组织机构代码证",
          "mdfrId": "测试用户_110010",
          "number": "5",
          "modifEffDtFlg": "0"
        }
      ],
      "total": 149,
      "pageCount": 0,
      "pageNo": 1,
      "hasPrevious": false,
      "hasNext": false,
      "result": [
        {
          "cellStyleMap": {},
          "key": "20000031162900009033220::06",
          "acctId": "2000000011",
          "custId": "c2000000011",
          "custName": "c2000000011",
          "orgId": "BR_0011",
          "orgNum": 110011,
          "orgName": "测试机构_BR_0011",
          "relaStatus": "06",
          "relaStatusDesc": "修改审批中",
          "validFlg": "1",
          "opeTm": 1585984994000,
          "oprEmpId": "110011",
          "oprEmpName": "测试用户_110011",
          "oprType": "2",
          "bizTypeCd": "06",
          "taskNum": "1000001782",
          "cerNum": "c2000000011",
          "empId": "110011",
          "empName": "测试用户_g011",
          "belongOrgId": "g011",
          "belongOrgNum": "g011",
          "belongOrgName": "测试机构_g011",
          "belongDept": "05",
          "relaRoleId": "001",
          "relaRoleDesc": "营销人",
          "relaRatio": 0.2,
          "effDt": 1585929600000,
          "invalidDt": 32503564800000,
          "relaRatioDesc": "  20",
          "bizType": "公司存款",
          "cerTypeCd": "10",
          "cerTypeDesc": "组织机构代码证",
          "mdfrId": "测试用户_110011",
          "number": "1",
          "modifEffDtFlg": "0"
        },
        {
          "cellStyleMap": {},
          "key": "20000031162900009033220::06",
          "acctId": "2000000012",
          "custId": "c2000000012",
          "custName": "c2000000012",
          "orgId": "BR_0012",
          "orgNum": 110012,
          "orgName": "测试机构_BR_0012",
          "relaStatus": "06",
          "relaStatusDesc": "修改审批中",
          "validFlg": "1",
          "opeTm": 1585984994000,
          "oprEmpId": "110012",
          "oprEmpName": "测试用户_110012",
          "oprType": "2",
          "bizTypeCd": "06",
          "taskNum": "1000001782",
          "cerNum": "c2000000012",
          "empId": "110012",
          "empName": "测试用户_g012",
          "belongOrgId": "g012",
          "belongOrgNum": "g012",
          "belongOrgName": "测试机构_g012",
          "belongDept": "01",
          "relaRoleId": "001",
          "relaRoleDesc": "营销人",
          "relaRatio": 0.1,
          "effDt": 1585929600000,
          "invalidDt": 32503564800000,
          "relaRatioDesc": "  10",
          "bizType": "公司存款",
          "cerTypeCd": "10",
          "cerTypeDesc": "组织机构代码证",
          "mdfrId": "测试用户_110012",
          "number": "1",
          "modifEffDtFlg": "0"
        },
        {
          "cellStyleMap": {},
          "key": "20000031162900009033220::06",
          "acctId": "2000000013",
          "custId": "c2000000013",
          "custName": "c2000000013",
          "orgId": "BR_0013",
          "orgNum": 110013,
          "orgName": "测试机构_BR_0013",
          "relaStatus": "06",
          "relaStatusDesc": "修改审批中",
          "validFlg": "1",
          "opeTm": 1585984994000,
          "oprEmpId": "110013",
          "oprEmpName": "测试用户_110013",
          "oprType": "2",
          "bizTypeCd": "06",
          "taskNum": "1000001782",
          "cerNum": "c2000000013",
          "empId": "110013",
          "empName": "测试用户_g013",
          "belongOrgId": "g013",
          "belongOrgNum": "g013",
          "belongOrgName": "测试机构_g013",
          "belongDept": "04",
          "relaRoleId": "001",
          "relaRoleDesc": "营销人",
          "relaRatio": 0.2,
          "effDt": 1585929600000,
          "invalidDt": 32503564800000,
          "relaRatioDesc": "  20",
          "bizType": "公司存款",
          "cerTypeCd": "10",
          "cerTypeDesc": "组织机构代码证",
          "mdfrId": "测试用户_110013",
          "number": "1",
          "modifEffDtFlg": "0"
        },
        {
          "cellStyleMap": {},
          "key": "01090321000125103001820::06",
          "acctId": "2000000014",
          "custId": "c2000000014",
          "custName": "c2000000014",
          "orgId": "BR_0014",
          "orgNum": 110014,
          "orgName": "测试机构_BR_0014",
          "relaStatus": "03",
          "relaStatusDesc": "关联审批中",
          "validFlg": "1",
          "opeTm": 1577264077000,
          "oprEmpId": "110014",
          "oprEmpName": "测试用户_110014",
          "oprType": "1",
          "bizTypeCd": "06",
          "taskNum": "1000002115",
          "cerNum": "c2000000014",
          "empId": "110014",
          "empName": "测试用户_g014",
          "belongOrgId": "g014",
          "belongOrgNum": "g014",
          "belongOrgName": "测试机构_g014",
          "belongDept": "05",
          "relaRoleId": "002",
          "relaRoleDesc": "维护人",
          "relaRatio": 0.33,
          "effDt": 1577203200000,
          "invalidDt": 32503564800000,
          "relaRatioDesc": "  33",
          "bizType": "公司存款",
          "cerTypeCd": "10",
          "cerTypeDesc": "组织机构代码证",
          "mdfrId": "测试用户_110014",
          "number": "2",
          "modifEffDtFlg": "0"
        },
        {
          "cellStyleMap": {},
          "key": "01090321000125103001820::06",
          "acctId": "2000000015",
          "custId": "c2000000015",
          "custName": "c2000000015",
          "orgId": "BR_0015",
          "orgNum": 110015,
          "orgName": "测试机构_BR_0015",
          "relaStatus": "03",
          "relaStatusDesc": "关联审批中",
          "validFlg": "1",
          "opeTm": 1577264077000,
          "oprEmpId": "110015",
          "oprEmpName": "测试用户_110015",
          "oprType": "1",
          "bizTypeCd": "06",
          "taskNum": "1000002115",
          "cerNum": "c2000000015",
          "empId": "110015",
          "empName": "测试用户_g015",
          "belongOrgId": "g015",
          "belongOrgNum": "g015",
          "belongOrgName": "测试机构_g015",
          "belongDept": "05",
          "relaRoleId": "001",
          "relaRoleDesc": "营销人",
          "relaRatio": 0.2,
          "effDt": 1577203200000,
          "invalidDt": 32503564800000,
          "relaRatioDesc": "  20",
          "bizType": "公司存款",
          "cerTypeCd": "10",
          "cerTypeDesc": "组织机构代码证",
          "mdfrId": "测试用户_110015",
          "number": "2",
          "modifEffDtFlg": "0"
        },
        {
          "cellStyleMap": {},
          "key": "01090343000120109107423_test_10172::06",
          "acctId": "2000000016",
          "custId": "c2000000016",
          "custName": "c2000000016",
          "orgId": "BR_0016",
          "orgNum": 110016,
          "orgName": "测试机构_BR_0016",
          "relaStatus": "03",
          "relaStatusDesc": "关联审批中",
          "validFlg": "1",
          "opeTm": 1577240566000,
          "oprEmpId": "110016",
          "oprEmpName": "测试用户_110016",
          "oprType": "1",
          "bizTypeCd": "06",
          "taskNum": "1000002113",
          "cerNum": "c2000000016",
          "empId": "110016",
          "empName": "测试用户_g016",
          "belongOrgId": "g016",
          "belongOrgNum": "g016",
          "belongOrgName": "测试机构_g016",
          "belongDept": "05",
          "relaRoleId": "001",
          "relaRoleDesc": "营销人",
          "relaRatio": 0.23,
          "effDt": 1577203200000,
          "invalidDt": 32503564800000,
          "relaRatioDesc": "  23",
          "bizType": "公司存款",
          "cerTypeCd": "10",
          "cerTypeDesc": "组织机构代码证",
          "mdfrId": "测试用户_110016",
          "number": "3",
          "modifEffDtFlg": "0"
        },
        {
          "cellStyleMap": {},
          "key": "01090343000120109107423_test_10172::06",
          "acctId": "2000000017",
          "custId": "c2000000017",
          "custName": "c2000000017",
          "orgId": "BR_0017",
          "orgNum": 110017,
          "orgName": "测试机构_BR_0017",
          "relaStatus": "03",
          "relaStatusDesc": "关联审批中",
          "validFlg": "1",
          "opeTm": 1577240566000,
          "oprEmpId": "110017",
          "oprEmpName": "测试用户_110017",
          "oprType": "1",
          "bizTypeCd": "06",
          "taskNum": "1000002113",
          "cerNum": "c2000000017",
          "empId": "110017",
          "empName": "测试用户_g017",
          "belongOrgId": "g017",
          "belongOrgNum": "g017",
          "belongOrgName": "测试机构_g017",
          "belongDept": "04",
          "relaRoleId": "002",
          "relaRoleDesc": "维护人",
          "relaRatio": 0.13,
          "effDt": 1577203200000,
          "invalidDt": 32503564800000,
          "relaRatioDesc": "  13",
          "bizType": "公司存款",
          "cerTypeCd": "10",
          "cerTypeDesc": "组织机构代码证",
          "mdfrId": "测试用户_110017",
          "number": "3",
          "modifEffDtFlg": "0"
        },
        {
          "cellStyleMap": {},
          "key": "01090321000120102096005::06",
          "acctId": "2000000018",
          "custId": "c2000000018",
          "custName": "c2000000018",
          "orgId": "BR_0018",
          "orgNum": 110018,
          "orgName": "测试机构_BR_0018",
          "relaStatus": "06",
          "relaStatusDesc": "修改审批中",
          "validFlg": "1",
          "opeTm": 1573457161000,
          "oprEmpId": "110018",
          "oprEmpName": "测试用户_110018",
          "oprType": "2",
          "bizTypeCd": "06",
          "taskNum": "1000002032",
          "cerNum": "c2000000018",
          "empId": "110018",
          "empName": "测试用户_g018",
          "belongOrgId": "g018",
          "belongOrgNum": "g018",
          "belongOrgName": "测试机构_g018",
          "belongDept": "05",
          "relaRoleId": "002",
          "relaRoleDesc": "维护人",
          "relaRatio": 0.13,
          "effDt": 1573401600000,
          "invalidDt": 32503564800000,
          "relaRatioDesc": "  13",
          "bizType": "公司存款",
          "cerTypeCd": "10",
          "cerTypeDesc": "组织机构代码证",
          "mdfrId": "测试用户_110018",
          "number": "4",
          "modifEffDtFlg": "0"
        },
        {
          "cellStyleMap": {},
          "key": "01090321000120102096005::06",
          "acctId": "2000000019",
          "custId": "c2000000019",
          "custName": "c2000000019",
          "orgId": "BR_0019",
          "orgNum": 110019,
          "orgName": "测试机构_BR_0019",
          "relaStatus": "06",
          "relaStatusDesc": "修改审批中",
          "validFlg": "1",
          "opeTm": 1573457161000,
          "oprEmpId": "110019",
          "oprEmpName": "测试用户_110019",
          "oprType": "2",
          "bizTypeCd": "06",
          "taskNum": "1000002032",
          "cerNum": "c2000000019",
          "empId": "110019",
          "empName": "测试用户_g019",
          "belongOrgId": "g019",
          "belongOrgNum": "g019",
          "belongOrgName": "测试机构_g019",
          "belongDept": "05",
          "relaRoleId": "001",
          "relaRoleDesc": "营销人",
          "relaRatio": 0.33,
          "effDt": 1573401600000,
          "invalidDt": 32503564800000,
          "relaRatioDesc": "  33",
          "bizType": "公司存款",
          "cerTypeCd": "10",
          "cerTypeDesc": "组织机构代码证",
          "mdfrId": "测试用户_110019",
          "number": "4",
          "modifEffDtFlg": "0"
        },
        {
          "cellStyleMap": {},
          "key": "01090321000120102108561::06",
          "acctId": "2000000020",
          "custId": "c2000000020",
          "custName": "c2000000020",
          "orgId": "BR_0020",
          "orgNum": 110020,
          "orgName": "测试机构_BR_0020",
          "relaStatus": "03",
          "relaStatusDesc": "关联审批中",
          "validFlg": "1",
          "opeTm": 1573454242000,
          "oprEmpId": "110020",
          "oprEmpName": "测试用户_110020",
          "oprType": "1",
          "bizTypeCd": "06",
          "taskNum": "1000002022",
          "cerNum": "c2000000020",
          "empId": "110020",
          "empName": "测试用户_g020",
          "belongOrgId": "g020",
          "belongOrgNum": "g020",
          "belongOrgName": "测试机构_g020",
          "belongDept": "05",
          "relaRoleId": "001",
          "relaRoleDesc": "营销人",
          "relaRatio": 0.1,
          "effDt": 1572883200000,
          "invalidDt": 32503564800000,
          "relaRatioDesc": "  10",
          "bizType": "公司存款",
          "cerTypeCd": "10",
          "cerTypeDesc": "组织机构代码证",
          "mdfrId": "测试用户_110020",
          "number": "5",
          "modifEffDtFlg": "0"
        }
      ],
      "startOfPage": 0
    }
  }
}
