{"code":"200","message":"成功","data":{"pageSize":10,"rows":[{"teamId":"1","teamName":"test1","teamLeaderEmpno":null,"teamTypeCd":"01","teamType":"个人团队","belongOrg":"ICOD501420","teamCharCd":"01","teamChar":"规范性考核团队","teamDesc":null,"modifTm":null,"setupTm":null,"setupPersonId":null,"belongLine":"03","belongLineDesc":"市场线","belongOrgName":null,"mdfrId":null,"effDt":"2019-04-18","invalidDt":"2019-04-29","teamMember":null,"teamLeader":null,"assPropNum":null,"assPropName":null,"assEmpNum":null},{"teamId":"1000000097","teamName":"中关村分行+京北管理部_中关村直属行办公室主任_1000000097","teamLeaderEmpno":null,"teamTypeCd":"01","teamType":"个人团队","belongOrg":"DUM01","teamCharCd":"01","teamChar":"规范性考核团队","teamDesc":null,"modifTm":null,"setupTm":null,"setupPersonId":null,"belongLine":"03","belongLineDesc":"市场线","belongOrgName":"中关村分行+京北管理部","mdfrId":null,"effDt":null,"invalidDt":null,"teamMember":null,"teamLeader":null,"assPropNum":null,"assPropName":null,"assEmpNum":null},{"teamId":"1000000099","teamName":"中关村分行+京北管理部_中关村直属行办公室主任_1000000099","teamLeaderEmpno":null,"teamTypeCd":"01","teamType":"个人团队","belongOrg":"DUM01","teamCharCd":"01","teamChar":"规范性考核团队","teamDesc":null,"modifTm":null,"setupTm":null,"setupPersonId":null,"belongLine":"03","belongLineDesc":"市场线","belongOrgName":"中关村分行+京北管理部","mdfrId":null,"effDt":null,"invalidDt":null,"teamMember":null,"teamLeader":null,"assPropNum":null,"assPropName":null,"assEmpNum":null},{"teamId":"1000000113","teamName":"双榆树管辖行_新街口北大街支行_1000000113","teamLeaderEmpno":null,"teamTypeCd":"02","teamType":"机构团队","belongOrg":"IOODSZ6007001","teamCharCd":"02","teamChar":"劳动竞赛考核团队","teamDesc":null,"modifTm":null,"setupTm":null,"setupPersonId":null,"belongLine":"03","belongLineDesc":"市场线","belongOrgName":"双榆树支行","mdfrId":null,"effDt":null,"invalidDt":null,"teamMember":null,"teamLeader":null,"assPropNum":null,"assPropName":null,"assEmpNum":null},{"teamId":"1000000118","teamName":"中关村分行+京北管理部_中关村直属行办公室主任_1000000118","teamLeaderEmpno":null,"teamTypeCd":"01","teamType":"个人团队","belongOrg":"DUM01","teamCharCd":"02","teamChar":"劳动竞赛考核团队","teamDesc":null,"modifTm":null,"setupTm":null,"setupPersonId":null,"belongLine":"03","belongLineDesc":"市场线","belongOrgName":"中关村分行+京北管理部","mdfrId":null,"effDt":null,"invalidDt":null,"teamMember":null,"teamLeader":null,"assPropNum":null,"assPropName":null,"assEmpNum":null},{"teamId":"1000000119","teamName":"金运管辖行_中关村直属行办公室主任_1000000119","teamLeaderEmpno":null,"teamTypeCd":"01","teamType":"个人团队","belongOrg":"IOODSZ5000404","teamCharCd":"02","teamChar":"劳动竞赛考核团队","teamDesc":null,"modifTm":null,"setupTm":null,"setupPersonId":null,"belongLine":"03","belongLineDesc":"市场线","belongOrgName":"金运管辖行","mdfrId":null,"effDt":null,"invalidDt":null,"teamMember":null,"teamLeader":null,"assPropNum":null,"assPropName":null,"assEmpNum":null},{"teamId":"1000000124","teamName":"中关村分行+京北管理部_中关村直属行办公室主任_1000000124","teamLeaderEmpno":null,"teamTypeCd":"01","teamType":"个人团队","belongOrg":"DUM01","teamCharCd":"02","teamChar":"劳动竞赛考核团队","teamDesc":null,"modifTm":null,"setupTm":null,"setupPersonId":null,"belongLine":"03","belongLineDesc":"市场线","belongOrgName":"中关村分行+京北管理部","mdfrId":null,"effDt":null,"invalidDt":null,"teamMember":null,"teamLeader":null,"assPropNum":null,"assPropName":null,"assEmpNum":null},{"teamId":"1000000125","teamName":"中关村分行_金运管辖行_1000000125","teamLeaderEmpno":null,"teamTypeCd":"02","teamType":"机构团队","belongOrg":"IOODSZ4000348","teamCharCd":"02","teamChar":"劳动竞赛考核团队","teamDesc":null,"modifTm":null,"setupTm":null,"setupPersonId":null,"belongLine":"03","belongLineDesc":"市场线","belongOrgName":"中关村分行","mdfrId":null,"effDt":null,"invalidDt":null,"teamMember":null,"teamLeader":null,"assPropNum":null,"assPropName":null,"assEmpNum":null},{"teamId":"1000000126","teamName":"中关村分行+京北管理部_阜裕管辖行_1000000126","teamLeaderEmpno":null,"teamTypeCd":"02","teamType":"机构团队","belongOrg":"DUM01","teamCharCd":"01","teamChar":"规范性考核团队","teamDesc":null,"modifTm":null,"setupTm":null,"setupPersonId":null,"belongLine":"03","belongLineDesc":"市场线","belongOrgName":"中关村分行+京北管理部","mdfrId":null,"effDt":null,"invalidDt":null,"teamMember":null,"teamLeader":null,"assPropNum":null,"assPropName":null,"assEmpNum":null},{"teamId":"1000000129","teamName":"中关村分行+京北管理部_互联网金融中心直属行_1000000129","teamLeaderEmpno":null,"teamTypeCd":"02","teamType":"机构团队","belongOrg":"DUM01","teamCharCd":"02","teamChar":"劳动竞赛考核团队","teamDesc":null,"modifTm":null,"setupTm":null,"setupPersonId":null,"belongLine":"03","belongLineDesc":"市场线","belongOrgName":"中关村分行+京北管理部","mdfrId":null,"effDt":null,"invalidDt":null,"teamMember":null,"teamLeader":null,"assPropNum":null,"assPropName":null,"assEmpNum":null}],"total":32,"pageCount":0,"pageNo":1,"hasPrevious":false,"hasNext":false,"result":[{"teamId":"1","teamName":"test1","teamLeaderEmpno":null,"teamTypeCd":"01","teamType":"个人团队","belongOrg":"ICOD501420","teamCharCd":"01","teamChar":"规范性考核团队","teamDesc":null,"modifTm":null,"setupTm":null,"setupPersonId":null,"belongLine":"03","belongLineDesc":"市场线","belongOrgName":null,"mdfrId":null,"effDt":"2019-04-18","invalidDt":"2019-04-29","teamMember":null,"teamLeader":null,"assPropNum":null,"assPropName":null,"assEmpNum":null},{"teamId":"1000000097","teamName":"中关村分行+京北管理部_中关村直属行办公室主任_1000000097","teamLeaderEmpno":null,"teamTypeCd":"01","teamType":"个人团队","belongOrg":"DUM01","teamCharCd":"01","teamChar":"规范性考核团队","teamDesc":null,"modifTm":null,"setupTm":null,"setupPersonId":null,"belongLine":"03","belongLineDesc":"市场线","belongOrgName":"中关村分行+京北管理部","mdfrId":null,"effDt":null,"invalidDt":null,"teamMember":null,"teamLeader":null,"assPropNum":null,"assPropName":null,"assEmpNum":null},{"teamId":"1000000099","teamName":"中关村分行+京北管理部_中关村直属行办公室主任_1000000099","teamLeaderEmpno":null,"teamTypeCd":"01","teamType":"个人团队","belongOrg":"DUM01","teamCharCd":"01","teamChar":"规范性考核团队","teamDesc":null,"modifTm":null,"setupTm":null,"setupPersonId":null,"belongLine":"03","belongLineDesc":"市场线","belongOrgName":"中关村分行+京北管理部","mdfrId":null,"effDt":null,"invalidDt":null,"teamMember":null,"teamLeader":null,"assPropNum":null,"assPropName":null,"assEmpNum":null},{"teamId":"1000000113","teamName":"双榆树管辖行_新街口北大街支行_1000000113","teamLeaderEmpno":null,"teamTypeCd":"02","teamType":"机构团队","belongOrg":"IOODSZ6007001","teamCharCd":"02","teamChar":"劳动竞赛考核团队","teamDesc":null,"modifTm":null,"setupTm":null,"setupPersonId":null,"belongLine":"03","belongLineDesc":"市场线","belongOrgName":"双榆树支行","mdfrId":null,"effDt":null,"invalidDt":null,"teamMember":null,"teamLeader":null,"assPropNum":null,"assPropName":null,"assEmpNum":null},{"teamId":"1000000118","teamName":"中关村分行+京北管理部_中关村直属行办公室主任_1000000118","teamLeaderEmpno":null,"teamTypeCd":"01","teamType":"个人团队","belongOrg":"DUM01","teamCharCd":"02","teamChar":"劳动竞赛考核团队","teamDesc":null,"modifTm":null,"setupTm":null,"setupPersonId":null,"belongLine":"03","belongLineDesc":"市场线","belongOrgName":"中关村分行+京北管理部","mdfrId":null,"effDt":null,"invalidDt":null,"teamMember":null,"teamLeader":null,"assPropNum":null,"assPropName":null,"assEmpNum":null},{"teamId":"1000000119","teamName":"金运管辖行_中关村直属行办公室主任_1000000119","teamLeaderEmpno":null,"teamTypeCd":"01","teamType":"个人团队","belongOrg":"IOODSZ5000404","teamCharCd":"02","teamChar":"劳动竞赛考核团队","teamDesc":null,"modifTm":null,"setupTm":null,"setupPersonId":null,"belongLine":"03","belongLineDesc":"市场线","belongOrgName":"金运管辖行","mdfrId":null,"effDt":null,"invalidDt":null,"teamMember":null,"teamLeader":null,"assPropNum":null,"assPropName":null,"assEmpNum":null},{"teamId":"1000000124","teamName":"中关村分行+京北管理部_中关村直属行办公室主任_1000000124","teamLeaderEmpno":null,"teamTypeCd":"01","teamType":"个人团队","belongOrg":"DUM01","teamCharCd":"02","teamChar":"劳动竞赛考核团队","teamDesc":null,"modifTm":null,"setupTm":null,"setupPersonId":null,"belongLine":"03","belongLineDesc":"市场线","belongOrgName":"中关村分行+京北管理部","mdfrId":null,"effDt":null,"invalidDt":null,"teamMember":null,"teamLeader":null,"assPropNum":null,"assPropName":null,"assEmpNum":null},{"teamId":"1000000125","teamName":"中关村分行_金运管辖行_1000000125","teamLeaderEmpno":null,"teamTypeCd":"02","teamType":"机构团队","belongOrg":"IOODSZ4000348","teamCharCd":"02","teamChar":"劳动竞赛考核团队","teamDesc":null,"modifTm":null,"setupTm":null,"setupPersonId":null,"belongLine":"03","belongLineDesc":"市场线","belongOrgName":"中关村分行","mdfrId":null,"effDt":null,"invalidDt":null,"teamMember":null,"teamLeader":null,"assPropNum":null,"assPropName":null,"assEmpNum":null},{"teamId":"1000000126","teamName":"中关村分行+京北管理部_阜裕管辖行_1000000126","teamLeaderEmpno":null,"teamTypeCd":"02","teamType":"机构团队","belongOrg":"DUM01","teamCharCd":"01","teamChar":"规范性考核团队","teamDesc":null,"modifTm":null,"setupTm":null,"setupPersonId":null,"belongLine":"03","belongLineDesc":"市场线","belongOrgName":"中关村分行+京北管理部","mdfrId":null,"effDt":null,"invalidDt":null,"teamMember":null,"teamLeader":null,"assPropNum":null,"assPropName":null,"assEmpNum":null},{"teamId":"1000000129","teamName":"中关村分行+京北管理部_互联网金融中心直属行_1000000129","teamLeaderEmpno":null,"teamTypeCd":"02","teamType":"机构团队","belongOrg":"DUM01","teamCharCd":"02","teamChar":"劳动竞赛考核团队","teamDesc":null,"modifTm":null,"setupTm":null,"setupPersonId":null,"belongLine":"03","belongLineDesc":"市场线","belongOrgName":"中关村分行+京北管理部","mdfrId":null,"effDt":null,"invalidDt":null,"teamMember":null,"teamLeader":null,"assPropNum":null,"assPropName":null,"assEmpNum":null}],"startOfPage":0}}
